<ZT2Strings>
<entityname>
   <!--animal names-->
      <Spnctr>Sphenonectris</Spnctr>
      <Spnctr_stt>Sphenonectris</Spnctr_stt>
      <Spnctr_lower>The Sphenonectris</Spnctr_lower>
      <Spnctr_ltt>
         <color r="255" g="248" b="178">
            <b>Sphenonectris</b>
         </color>
         <br/>
         Cick to select the Sphenonectris.
      </Spnctr_ltt>
</entityname>
<zoopedia_spnctr>
 <entry>Sphenonectris</entry>
 <text>
  <cell pady="0" width="1000"/>
  <p/>
  <cell width="260"/>
  <cell width="640" height="320" bgimg="ui/zoopedia/topCellBg.dds">
   <cell width="600" padx="20" pady="20">
   
               <cell width="284">
						 <cell width="96" bgimg="ui/zoopedia/littleBox-128.tga">
						  <img src="entities/units/animals/Spnctr/Spnctr_Adult_F_icon.dds" sx="0" sy="0" sw="64" sh="64" height="96" width="96"/>
						 </cell>
						 <cell width="16">
						  <img src="ui/zoopedia/icon_male.dds" sx="0" sy="0" sw="64" sh="64" width="16" height="16"/>
						 </cell>
						 <cell width="16">
						  <img src="ui/zoopedia/icon_female.dds" sx="0" sy="0" sw="64" sh="64" width="16" height="16"/>
						 </cell>
						 <cell width="156"/>
                  <br/>   
                  <cell width="32" pady="0">               
                     <img src="ui/zoopedia/extinct.dds" sx="0" sy="0" sw="64" sh="64" width="32" height="32"/>
                  </cell>                 
                  <cell width="224" padx="10" pady="0">
                     <color r="255" g="255" b="255">
                     Conservation status:
                     <br/>
                        <color r="0" g="255" b="0">
                      Extinct
                        </color>
                     </color>                  
                  </cell>
               </cell>   
   
    <cell width="128">
     <color r="255" g="255" b="255">Coast<br/></color>
     <img src="ui/icon_biomes/icon_reef.dds" sx="0" sy="0" sw="128" sh="128" width="96" height="96"/>
    </cell>
    <cell width="128">
     <color r="255" g="255" b="255">Tetis sea<br/></color> 
     <img src="ui/icon_maplocations/reef_warm_oceans_worldwide.dds" sx="0" sy="0" sw="256" sh="256" width="96" height="96"/>
    </cell>
    <br/>
    <cell width="284" pady="10">
     <color r="255" g="255" b="255">Clas: Thelodonti <i>(Thelodontis)</i><br/>Order: Furcacaudiformes <i>(Furcacauda)</i><br/>Family: Furcacaudiidae <i>(Furcacauda)</i><br/>Genera: <i>Sphenonectris</i><br/>Species: <i>S. Turnerae</i>
     </color>
    </cell>
    <cell width="256" pady="10">
     <img src="UI/zoopedia/biome/reef_zoopedia_biomebrush.dds" sx="0" sy="0" sw="256" sh="85"/>
    </cell>
   </cell>
  </cell>
  <p/>
  <p/>
  <cell width="260"/>
  <cell width="300">
   <cell width="64">
    <img src="ui/zoopedia/fact-icon64.tga" sx="0" sy="0" sw="64" sh="64"/>
   </cell>
   <cell width="176">
    <color r="255" g="255" b="255">
     <font name="arial" size="12" shadowx="2" shadowy="1" shadowa="50">Facts of Sphenonectris</font>
    </color>
   </cell>
   <p/>
   <cell width="280" bgimg="ui/zoopedia/factBG.tga" padx="10">
    <p/>
    <cell width="32" pady="10">
     <img src="ui/zoopedia/fact-bullet.tga" sx="0" sy="0" sw="32" sh="32"/>
    </cell>
    <cell width="202" pady="10">
     <color r="255" g="255" b="255">Sphenonectris measure 12 cm.</color>
    </cell>
	<cell width="32" pady="10">
		<img src="ui/zoopedia/fact-bullet.tga" sx="0" sy="0" sw="32" sh="32"/>
	</cell>    
    <cell width="202" pady="10">
     <color r="255" g="255" b="255">Sphenonectris looks like a Furcacauda.</color>
    </cell>
  </cell>
  </cell>
  <cell width="340">
   <color r="255" g="248" b="178">
    Need 1/2 stars to adopt the Sphenonectris.
   </color>
   <p/>Sphenonectris is a fish that belongs to the group of Furcacaudiformes, an order of thelodontes with similar shapes. The tail furcacaudiformes have a characteristic shape, more or less square. Sphenonectris lived in the Devonian, and possibly a descendant of Furcacauda, the Silurian. The group of furcacaudiformes is small compared with other groups thelodontes who lived until the Devonian. Other similar Furcacaudiformes the same group were Canonia, Cometicerus and Drepanolepis, besides Furcacauda.
   </cell>
  <p/>
  <cell width="260"/>
  <cell width="620">
   Info from Wikipedia
  <p/>Maked by Imago
  </cell>
 </text>
</zoopedia_spnctr>
</ZT2Strings>